pyno/__init__.py
pyno/browser_preview.py
pyno/components.py
pyno/custom_tags.py
pyno/html_tags_autocomplete.py
pyno/parser.py
pyno/stylesheets.py
pyno/tree_model.py
pyno/wsgi_interface.py
pyno-0.0.18.dist-info/LICENSE
pyno-0.0.18.dist-info/METADATA
pyno-0.0.18.dist-info/WHEEL
pyno-0.0.18.dist-info/top_level.txt
pyno-0.0.18.dist-info/RECORD
