Metadata-Version: 2.1
Name: pyno
Version: 0.0.18
Summary: A framework for building html, svg and other structured text in Python
Home-page: https://gitlab.com/jvincentl/Pyno
Author: Jackie Vincent Larsen
Author-email: jackie.v.larsen@gmail.com
License: UNKNOWN
Keywords: web-development,web
Platform: UNKNOWN
Classifier: License :: OSI Approved :: MIT License
Classifier: Programming Language :: Python
Classifier: Programming Language :: Python :: 3
Requires-Dist: beautifulsoup4
Requires-Dist: werkzeug
